Metadata-Version: 2.1
Name: superoptimize
Version: 1.0.2
Summary: superoptimzer Python Binding
Home-page: http://www.python-ogre.org/
Author: Lakin Wecker, Roman Yakovenko, Andy Miller
Author-email: python-ogre-developers@googlegroups.com
License: LGPL
Platform: UNKNOWN
